LICENSE
MANIFEST.in
README.md
setup.py
openEuler/__init__.py
openEuler/openEuler.py
openEuler/openEuler_core_src.txt
openEuler/pkg_info/openEuler_22.03-LTS-SP1_x86_64_Core.json
openEuler/pkg_info/openEuler_22.03-LTS-SP1_x86_64_EPOL.json
openEuler/pkg_info/openEuler_22.03-LTS-SP1_x86_64_Everything.json
openEuler/pkg_info/openEuler_22.03-LTS-SP1_x86_64_OS.json
openEuler/pkg_info/openEuler_22.03-LTS-SP1_x86_64_update.json
openEuler/pkg_info/openEuler_22.03-LTS-SP2_x86_64_Core.json
openEuler/pkg_info/openEuler_22.03-LTS-SP2_x86_64_EPOL.json
openEuler/pkg_info/openEuler_22.03-LTS-SP2_x86_64_Everything.json
openEuler/pkg_info/openEuler_22.03-LTS-SP2_x86_64_OS.json
openEuler/pkg_info/openEuler_22.03-LTS-SP2_x86_64_update.json
openEuler/pkg_info/openEuler_22.03-LTS-SP3_x86_64_Core.json
openEuler/pkg_info/openEuler_22.03-LTS-SP3_x86_64_EPOL.json
openEuler/pkg_info/openEuler_22.03-LTS-SP3_x86_64_Everything.json
openEuler/pkg_info/openEuler_22.03-LTS-SP3_x86_64_OS.json
openEuler/pkg_info/openEuler_22.03-LTS-SP3_x86_64_update.json
openEuler/pkg_info/openEuler_22.03-LTS-SP4_x86_64_Core.json
openEuler/pkg_info/openEuler_22.03-LTS-SP4_x86_64_EPOL.json
openEuler/pkg_info/openEuler_22.03-LTS-SP4_x86_64_Everything.json
openEuler/pkg_info/openEuler_22.03-LTS-SP4_x86_64_OS.json
openEuler/pkg_info/openEuler_22.03-LTS-SP4_x86_64_update.json
openEuler/pkg_info/openEuler_22.03-LTS_x86_64_Core.json
openEuler/pkg_info/openEuler_22.03-LTS_x86_64_EPOL.json
openEuler/pkg_info/openEuler_22.03-LTS_x86_64_Everything.json
openEuler/pkg_info/openEuler_22.03-LTS_x86_64_OS.json
openEuler/pkg_info/openEuler_22.03-LTS_x86_64_update.json
openEuler/pkg_info/openEuler_24.03-LTS-SP1_aarch64_Core.json
openEuler/pkg_info/openEuler_24.03-LTS-SP1_aarch64_EPOL.json
openEuler/pkg_info/openEuler_24.03-LTS-SP1_aarch64_Everything.json
openEuler/pkg_info/openEuler_24.03-LTS-SP1_aarch64_OS.json
openEuler/pkg_info/openEuler_24.03-LTS-SP1_aarch64_update.json
openEuler/pkg_info/openEuler_24.03-LTS-SP1_x86_64_Core.json
python3_openEuler.egg-info/PKG-INFO
python3_openEuler.egg-info/SOURCES.txt
python3_openEuler.egg-info/dependency_links.txt
python3_openEuler.egg-info/requires.txt
python3_openEuler.egg-info/top_level.txt